hexip/__init__.py
hexip/hexip.py
hexip-0.1.data/scripts/hexip
hexip-0.1.dist-info/DESCRIPTION.rst
hexip-0.1.dist-info/METADATA
hexip-0.1.dist-info/RECORD
hexip-0.1.dist-info/WHEEL
hexip-0.1.dist-info/metadata.json
hexip-0.1.dist-info/top_level.txt
