Metadata-Version: 2.0
Name: hexip
Version: 0.1
Summary: Tool to convert IPv4 address to hex. Useful for PXE boot config etc
Home-page: http://github.com/theunsa/hexpi
Author: Theuns Alberts
Author-email: theunsa@gmail.com
License: MIT
Platform: UNKNOWN
